fragment_sdk/__init__.py
fragment_sdk/ads.py
fragment_sdk/client.py
fragment_sdk/methods.py
fragment_sdk/premium.py
fragment_sdk/stars.py
fragment_sdk/errors/__init__.py
fragment_sdk/models/__init__.py
fragment_sdk/utils/extract_photo_src.py
fragment_sdk/utils/http_request.py
fragment_sdk/wallet/__init__.py
fragment_sdk-0.2.0.dist-info/licenses/LICENSE
fragment_sdk-0.2.0.dist-info/METADATA
fragment_sdk-0.2.0.dist-info/WHEEL
fragment_sdk-0.2.0.dist-info/top_level.txt
fragment_sdk-0.2.0.dist-info/RECORD
