Metadata-Version: 2.4
Name: fragment-sdk
Version: 0.2.0
Summary: Unofficial Fragment SDK for purchasing Telegram goods (Stars, Premium, Ads)
Author: whicencer
Project-URL: Source, https://github.com/whicencer/fragment-sdk
Project-URL: Community, https://t.me/fragmentsdk_chat
Keywords: fragment,telegram,api,client,library,python,sdk
Classifier: Programming Language :: Python :: 3
Classifier: Programming Language :: Python :: 3.10
Classifier: License :: OSI Approved :: MIT License
Classifier: Typing :: Typed
Requires-Python: >=3.10
License-File: LICENSE
Requires-Dist: requests>=2.32.0
Requires-Dist: beautifulsoup4>=4.14.0
Requires-Dist: tonutils>=0.5.0
Dynamic: license-file
